bobocep/__init__.py
bobocep/bobocep.py
bobocep/cep/__init__.py
bobocep/cep/action/__init__.py
bobocep/cep/action/action.py
bobocep/cep/action/handler.py
bobocep/cep/action/common/__init__.py
bobocep/cep/action/common/multi.py
bobocep/cep/engine/__init__.py
bobocep/cep/engine/engine.py
bobocep/cep/engine/task.py
bobocep/cep/engine/decider/__init__.py
bobocep/cep/engine/decider/decider.py
bobocep/cep/engine/decider/pubsub.py
bobocep/cep/engine/decider/run.py
bobocep/cep/engine/decider/runserial.py
bobocep/cep/engine/forwarder/__init__.py
bobocep/cep/engine/forwarder/forwarder.py
bobocep/cep/engine/forwarder/pubsub.py
bobocep/cep/engine/producer/__init__.py
bobocep/cep/engine/producer/producer.py
bobocep/cep/engine/producer/pubsub.py
bobocep/cep/engine/receiver/__init__.py
bobocep/cep/engine/receiver/pubsub.py
bobocep/cep/engine/receiver/receiver.py
bobocep/cep/engine/receiver/validator.py
bobocep/cep/event/__init__.py
bobocep/cep/event/action.py
bobocep/cep/event/complex.py
bobocep/cep/event/event.py
bobocep/cep/event/factory.py
bobocep/cep/event/history.py
bobocep/cep/event/simple.py
bobocep/cep/gen/__init__.py
bobocep/cep/gen/event.py
bobocep/cep/gen/event_id.py
bobocep/cep/gen/timestamp.py
bobocep/cep/phenom/__init__.py
bobocep/cep/phenom/phenom.py
bobocep/cep/phenom/pattern/__init__.py
bobocep/cep/phenom/pattern/builder.py
bobocep/cep/phenom/pattern/pattern.py
bobocep/cep/phenom/pattern/predicate.py
bobocep/dist/__init__.py
bobocep/dist/device.py
bobocep/dist/devman.py
bobocep/dist/dist.py
bobocep/dist/pubsub.py
bobocep/dist/tcp.py
bobocep/dist/crypto/__init__.py
bobocep/dist/crypto/aes.py
bobocep/dist/crypto/crypto.py
bobocep/setup/__init__.py
bobocep/setup/setup.py
bobocep/setup/simple.py
bobocep-1.2.2.dist-info/LICENSE
bobocep-1.2.2.dist-info/METADATA
bobocep-1.2.2.dist-info/WHEEL
bobocep-1.2.2.dist-info/top_level.txt
bobocep-1.2.2.dist-info/RECORD
