Metadata-Version: 2.1
Name: bobocep
Version: 1.2.2
Summary: A fault-tolerant Complex Event Processing engine designed for edge computing in Internet of Things systems.
Home-page: https://github.com/r3w0p/bobocep
Author: r3w0p
Author-email: rr33ww00pp@gmail.com
License: MIT
Keywords: complex event processing,distributed systems,edge computing,fault tolerance,internet of things,web of things
Classifier: Development Status :: 5 - Production/Stable
Classifier: Intended Audience :: Developers
Classifier: Intended Audience :: Science/Research
Classifier: License :: OSI Approved :: MIT License
Classifier: Natural Language :: English
Classifier: Programming Language :: Python :: 3.9
Classifier: Programming Language :: Python :: 3.10
Classifier: Programming Language :: Python :: 3.11
Classifier: Programming Language :: Python :: 3.12
Classifier: Topic :: Scientific/Engineering :: Information Analysis
Classifier: Topic :: Software Development :: Libraries :: Python Modules
Classifier: Topic :: System :: Distributed Computing
Classifier: Topic :: System :: Monitoring
License-File: LICENSE
Requires-Dist: jsonschema ==4.22.0
Requires-Dist: pycryptodome ==3.20.0
